dynalite_lib/__init__.py
dynalite_lib/__version__.py
dynalite_lib/const.py
dynalite_lib/dynalite.py
dynalite_lib/dynet.py
dynalite_lib/event.py
dynalite_lib/inbound.py
dynalite-0.1.32.dist-info/LICENSE.md
dynalite-0.1.32.dist-info/METADATA
dynalite-0.1.32.dist-info/WHEEL
dynalite-0.1.32.dist-info/top_level.txt
dynalite-0.1.32.dist-info/RECORD
