Metadata-Version: 2.1
Name: dynalite
Version: 0.1.32
Summary: An unofficial Dynalite DyNET interface.
Home-page: https://github.com/troykelly/python-dynalite
Author: Troy Kelly
Author-email: troy@troykelly.com
License: UNKNOWN
Project-URL: Bug Reports, https://github.com/troykelly/python-dynalite/issues
Project-URL: Source, https://github.com/troykelly/python-dynalite/
Keywords: homeautomation lighting philips dynalite
Platform: UNKNOWN
Classifier: Development Status :: 3 - Alpha
Classifier: Intended Audience :: Developers
Classifier: Topic :: Software Development :: Build Tools
Classifier: License :: OSI Approved :: MIT License
Classifier: Programming Language :: Python :: 3
Classifier: Programming Language :: Python :: 3.7
